vf/Exceptions.py
vf/OpencvProcessing.py
vf/VisionForge.py
vf/YOLOProcessing.py
vf/__init__.py
visionforge/Exceptions.py
visionforge/OpencvProcessing.py
visionforge/Tracking.py
visionforge/VisionForge.py
visionforge/YOLOProcessing.py
visionforge/__init__.py
visionforge/exception.py
VisionForge-1.0.0.dist-info/LICENSE
VisionForge-1.0.0.dist-info/METADATA
VisionForge-1.0.0.dist-info/WHEEL
VisionForge-1.0.0.dist-info/top_level.txt
VisionForge-1.0.0.dist-info/RECORD
