Metadata-Version: 2.1
Name: VisionForge
Version: 1.0.0
Summary: Tracking é um projeto de visão computacional que otimiza o rastreamento de objetos. Combina YOLOv8 para detecção em intervalos programados, reduzindo o custo computacional, e OpenCV para rastreamento em tempo real. Uma solução eficiente e econômica para monitoramento de objetos.
Home-page: https://github.com/Thigos/VisionForge
Author: Thiago Rodrigues
Author-email: 
License: AGPL-3.0 license
Project-URL: Documentation, https://github.com/Thigos/VisionForge/blob/main/README.md
Project-URL: Bug Reports, https://github.com/Thigos/VisionForge/issues
Project-URL: Source Code, https://github.com/Thigos/VisionForge
Classifier: Development Status :: 5 - Production/Stable
Classifier: Intended Audience :: Developers
Classifier: Topic :: Software Development :: Build Tools
Classifier: Programming Language :: Python :: 3.7
Classifier: Programming Language :: Python :: 3.8
Classifier: Programming Language :: Python :: 3.9
Classifier: License :: OSI Approved :: GNU Affero General Public License v3 or later (AGPLv3+)
Classifier: Operating System :: OS Independent
Requires-Python: >=3.7
License-File: LICENSE
Requires-Dist: ultralytics ~=8.0.118
Requires-Dist: opencv-python ~=4.6.0.66
Requires-Dist: numpy ~=1.23.5
Requires-Dist: torch >=1.8.1
